{
  "run_id": "20250401_143717",
  "operation": "consistency_check",
  "timestamp": "2025-04-01T14:37:17.905412",
  "timings": {
    "total_processing": 10.456573963165283
  },
  "field_counts": {},
  "resource_usage": {
    "memory_mb": 11.37109375,
    "cpu_percent": 0.0
  },
  "document_info": {
    "documents": {
      "plankart": {
        "filename": "PLANKART.pdf",
        "size": 531031
      },
      "bestemmelser": {
        "filename": "Bestemmelser.pdf",
        "size": 182997
      }
    }
  },
  "error": "500: 502: Server error '500 Internal Server Error' for url 'http://localhost:8001/api/extract-fields'\nFor more information check: https://developer.mozilla.org/en-US/docs/Web/HTTP/Status/500"
}